LICENSE
MANIFEST.in
README.rst
setup.py
sphinx_autodoc_annotation.py
sphinx_autodoc_annotation.egg-info/PKG-INFO
sphinx_autodoc_annotation.egg-info/SOURCES.txt
sphinx_autodoc_annotation.egg-info/dependency_links.txt
sphinx_autodoc_annotation.egg-info/requires.txt
sphinx_autodoc_annotation.egg-info/top_level.txt