Metadata-Version: 1.1
Name: sphinx-autodoc-annotation
Version: 1.0
Summary: Use Python 3 annotations in sphinx-enabled docstrings
Home-page: https://github.com/hsoft/sphinx-autodoc-annotation
Author: Virgil Dupras
Author-email: hsoft@hardcoded.net
License: BSD
Platform: UNKNOWN
Classifier: Intended Audience :: Developers
Classifier: License :: OSI Approved :: BSD License
Classifier: Programming Language :: Python :: 3.3
Classifier: Operating System :: OS Independent
Classifier: Topic :: Documentation
